MANIFEST.in
README.md
setup.cfg
setup.py
django_mqueue_livefeed.egg-info/PKG-INFO
django_mqueue_livefeed.egg-info/SOURCES.txt
django_mqueue_livefeed.egg-info/dependency_links.txt
django_mqueue_livefeed.egg-info/not-zip-safe
django_mqueue_livefeed.egg-info/requires.txt
django_mqueue_livefeed.egg-info/top_level.txt
mqueue_livefeed/__init__.py
mqueue_livefeed/admin.py
mqueue_livefeed/apps.py
mqueue_livefeed/conf.py
mqueue_livefeed/models.py
mqueue_livefeed/tests.py
mqueue_livefeed/urls.py
mqueue_livefeed/views.py
mqueue_livefeed/management/__init__.py
mqueue_livefeed/management/commands/__init__.py
mqueue_livefeed/management/commands/feed_mq.py
mqueue_livefeed/migrations/0001_initial.py
mqueue_livefeed/migrations/__init__.py
mqueue_livefeed/migrations/__pycache__/0001_initial.cpython-35.pyc
mqueue_livefeed/migrations/__pycache__/__init__.cpython-35.pyc
mqueue_livefeed/templates/mql/base.html
mqueue_livefeed/templates/mql/index.html
mqueue_livefeed/templates/mql/status.html
mqueue_livefeed/templates/mql/js/app.js
mqueue_livefeed/templates/mql/js/client.js
mqueue_livefeed/templates/mql/js/handlers.js
mqueue_livefeed/templatetags/__init__.py
mqueue_livefeed/templatetags/__init__.pyc
mqueue_livefeed/templatetags/mql.py
mqueue_livefeed/templatetags/mql.pyc
mqueue_livefeed/templatetags/__pycache__/__init__.cpython-35.pyc
mqueue_livefeed/templatetags/__pycache__/mql.cpython-35.pyc