Metadata-Version: 1.1
Name: django-mqueue-livefeed
Version: 0.3
Summary:  Real time events feed for Django Mqueue
Home-page: https://github.com/synw/django-mqueue-livefeed
Author: synw
Author-email: synwe@yahoo.com
License: UNKNOWN
Download-URL: https://github.com/synw/django-mqueue-livefeed/releases/tag/0.3
Keywords: django,websockets,events,logging
Platform: UNKNOWN
Classifier: Development Status :: 3 - Alpha
Classifier: Framework :: Django :: 1.9
Classifier: Intended Audience :: Developers
Classifier: License :: OSI Approved :: MIT License
Classifier: Programming Language :: Python :: 2.7
